django_coinpayments/__init__.py
django_coinpayments/admin.py
django_coinpayments/apps.py
django_coinpayments/coinpayments.py
django_coinpayments/exceptions.py
django_coinpayments/forms.py
django_coinpayments/models.py
django_coinpayments/tasks.py
django_coinpayments/urls.py
django_coinpayments/utils.py
django_coinpayments/views.py
django_coinpayments/migrations/0001_initial.py
django_coinpayments/migrations/0002_auto_20180428_1414.py
django_coinpayments/migrations/0003_payment_buyer_email.py
django_coinpayments/migrations/__init__.py
django_coinpayments/static/css/django_coinpayments.css
django_coinpayments/static/js/django_coinpayments.js
django_coinpayments/templates/django_coinpayments/base.html
django_coinpayments-0.1.4.dist-info/DESCRIPTION.rst
django_coinpayments-0.1.4.dist-info/METADATA
django_coinpayments-0.1.4.dist-info/RECORD
django_coinpayments-0.1.4.dist-info/WHEEL
django_coinpayments-0.1.4.dist-info/metadata.json
django_coinpayments-0.1.4.dist-info/top_level.txt
